equitweet.py
equitweet-0.0.1.dist-info/LICENSE
equitweet-0.0.1.dist-info/METADATA
equitweet-0.0.1.dist-info/WHEEL
equitweet-0.0.1.dist-info/top_level.txt
equitweet-0.0.1.dist-info/RECORD
