Metadata-Version: 2.1
Name: equitweet
Version: 0.0.1
Summary: A small package for collecting $finance tweets
Home-page: https://github.com/bcutrell/equitweet
Author: 
Author-email: bcutrell13@gmail.com
License: UNKNOWN
Platform: UNKNOWN
Classifier: Programming Language :: Python :: 3
Classifier: License :: OSI Approved :: MIT License
Classifier: Operating System :: OS Independent
Requires-Python: >=3.6.0
Requires-Dist: twitter
